README.md
README.rst
setup.cfg
setup.py
lps/__init__.py
lps/cli.py
lps/input_handler.py
lps/page_geometries.py
lps.egg-info/PKG-INFO
lps.egg-info/SOURCES.txt
lps.egg-info/dependency_links.txt
lps.egg-info/entry_points.txt
lps.egg-info/requires.txt
lps.egg-info/top_level.txt