Metadata-Version: 1.1
Name: lps
Version: 0.0.1
Summary: Lay out large print jobs as PDFs with alignment marks.
Home-page: https://github.com/cgspeck/largeprintsplitter
Author: Chris Speck
Author-email: cgspeck@gmail.com
License: UNKNOWN
Download-URL: https://github.com/cgspeck/largeprintsplitter/archive/0.0.1.tar.gz
Keywords: print,printing,layout,pdf,plan,engineering,fabrication
Platform: UNKNOWN
